{"0": [["0", "1.0"], ["9", "0.61"], ["49", "0.489"], ["24", "0.48"], ["42", "0.477"], ["3", "0.45"], ["31", "0.449"], ["15", "0.424"], ["7", "0.336"], ["1", "0.319"], ["10", "0.316"], ["35", "0.296"], ["39", "0.277"], ["11", "0.266"], ["2", "0.265"], ["41", "0.263"], ["37", "0.204"], ["5", "0.199"], ["43", "0.196"], ["26", "0.195"], ["6", "0.194"], ["8", "0.18"], ["46", "0.171"], ["29", "0.168"], ["4", "0.132"], ["44", "0.131"], ["45", "0.094"], ["40", "0.09"], ["17", "0.081"], ["20", "0.067"], ["18", "0.066"], ["34", "0.061"], ["32", "0.061"], ["13", "0.057"], ["12", "0.051"], ["28", "0.032"], ["14", "0.031"], ["21", "0.025"], ["23", "0.019"], ["48", "-0.014"], ["30", "-0.073"], ["16", "-0.092"], ["38", "-0.127"], ["33", "-0.138"], ["25", "-0.147"], ["27", "-0.151"], ["22", "-0.191"], ["36", "-0.191"], ["47", "-0.291"], ["19", "-0.321"]], "1": [["1", "1.0"], ["42", "0.643"], ["7", "0.491"], ["11", "0.481"], ["49", "0.474"], ["43", "0.425"], ["5", "0.409"], ["37", "0.376"], ["9", "0.374"], ["15", "0.356"], ["6", "0.338"], ["0", "0.319"], ["3", "0.299"], ["39", "0.289"], ["24", "0.279"], ["44", "0.277"], ["46", "0.274"], ["45", "0.269"], ["41", "0.259"], ["31", "0.256"], ["2", "0.213"], ["40", "0.211"], ["4", "0.159"], ["13", "0.154"], ["48", "0.143"], ["14", "0.114"], ["18", "0.107"], ["35", "0.1"], ["17", "0.07"], ["10", "0.059"], ["20", "0.057"], ["28", "0.036"], ["23", "0.036"], ["30", "0.032"], ["16", "0.025"], ["34", "-0.004"], ["8", "-0.019"], ["32", "-0.023"], ["19", "-0.036"], ["38", "-0.038"], ["25", "-0.039"], ["22", "-0.04"], ["29", "-0.044"], ["26", "-0.057"], ["33", "-0.081"], ["27", "-0.099"], ["21", "-0.145"], ["36", "-0.195"], ["12", "-0.197"], ["47", "-0.231"]], "2": [["2", "1.0"], ["6", "0.323"], ["34", "0.32"], ["31", "0.316"], ["27", "0.302"], ["40", "0.293"], ["9", "0.292"], ["15", "0.291"], ["0", "0.265"], ["41", "0.259"], ["13", "0.259"], ["42", "0.245"], ["17", "0.242"], ["28", "0.226"], ["46", "0.225"], ["35", "0.221"], ["1", "0.213"], ["30", "0.21"], ["20", "0.21"], ["10", "0.205"], ["16", "0.198"], ["5", "0.198"], ["7", "0.19"], ["11", "0.179"], ["14", "0.175"], ["49", "0.174"], ["37", "0.174"], ["43", "0.171"], ["48", "0.16"], ["29", "0.157"], ["25", "0.155"], ["33", "0.155"], ["24", "0.145"], ["32", "0.142"], ["38", "0.133"], ["3", "0.132"], ["45", "0.127"], ["26", "0.123"], ["21", "0.102"], ["23", "0.1"], ["44", "0.065"], ["19", "0.054"], ["22", "0.044"], ["18", "0.044"], ["39", "0.036"], ["47", "0.032"], ["12", "0.021"], ["4", "-0.0"], ["8", "-0.055"], ["36", "-0.149"]], "3": [["3", "1.0"], ["0", "0.45"], ["15", "0.397"], ["42", "0.393"], ["24", "0.344"], ["49", "0.32"], ["9", "0.309"], ["1", "0.299"], ["10", "0.261"], ["11", "0.243"], ["39", "0.221"], ["8", "0.212"], ["7", "0.184"], ["5", "0.168"], ["31", "0.165"], ["2", "0.132"], ["40", "0.113"], ["37", "0.11"], ["4", "0.095"], ["44", "0.092"], ["6", "0.061"], ["43", "0.055"], ["46", "0.037"], ["14", "0.001"], ["12", "-0.0"], ["32", "-0.023"], ["26", "-0.039"], ["45", "-0.04"], ["41", "-0.048"], ["23", "-0.051"], ["35", "-0.053"], ["20", "-0.067"], ["29", "-0.087"], ["18", "-0.09"], ["48", "-0.105"], ["22", "-0.113"], ["28", "-0.152"], ["17", "-0.157"], ["38", "-0.161"], ["21", "-0.187"], ["13", "-0.203"], ["34", "-0.228"], ["16", "-0.241"], ["36", "-0.253"], ["30", "-0.287"], ["33", "-0.293"], ["27", "-0.36"], ["25", "-0.361"], ["47", "-0.382"], ["19", "-0.402"]], "4": [["4", "1.0"], ["11", "0.374"], ["5", "0.325"], ["9", "0.309"], ["42", "0.264"], ["43", "0.255"], ["41", "0.228"], ["15", "0.212"], ["13", "0.21"], ["10", "0.203"], ["7", "0.187"], ["46", "0.186"], ["14", "0.184"], ["1", "0.159"], ["44", "0.139"], ["0", "0.132"], ["49", "0.126"], ["48", "0.114"], ["3", "0.095"], ["6", "0.067"], ["16", "0.065"], ["39", "0.065"], ["17", "0.059"], ["47", "0.048"], ["45", "0.048"], ["18", "0.032"], ["19", "0.001"], ["2", "-0.0"], ["8", "-0.006"], ["12", "-0.045"], ["40", "-0.076"], ["34", "-0.104"], ["20", "-0.142"], ["27", "-0.143"], ["31", "-0.143"], ["25", "-0.16"], ["35", "-0.176"], ["24", "-0.18"], ["37", "-0.214"], ["21", "-0.219"], ["33", "-0.225"], ["38", "-0.226"], ["26", "-0.277"], ["29", "-0.285"], ["30", "-0.296"], ["36", "-0.299"], ["23", "-0.31"], ["32", "-0.364"], ["28", "-0.376"], ["22", "-0.461"]], "5": [["5", "1.0"], ["42", "0.577"], ["11", "0.454"], ["1", "0.409"], ["49", "0.396"], ["7", "0.33"], ["4", "0.325"], ["15", "0.324"], ["44", "0.289"], ["9", "0.282"], ["43", "0.276"], ["46", "0.267"], ["39", "0.26"], ["13", "0.247"], ["6", "0.239"], ["37", "0.233"], ["41", "0.213"], ["48", "0.209"], ["0", "0.199"], ["2", "0.198"], ["45", "0.18"], ["10", "0.174"], ["14", "0.173"], ["3", "0.168"], ["40", "0.127"], ["31", "0.034"], ["18", "0.025"], ["16", "0.004"], ["12", "-0.002"], ["34", "-0.008"], ["20", "-0.021"], ["17", "-0.026"], ["23", "-0.031"], ["19", "-0.044"], ["8", "-0.048"], ["38", "-0.054"], ["24", "-0.057"], ["27", "-0.091"], ["35", "-0.101"], ["30", "-0.111"], ["28", "-0.116"], ["47", "-0.117"], ["25", "-0.129"], ["33", "-0.149"], ["22", "-0.171"], ["26", "-0.185"], ["29", "-0.207"], ["21", "-0.271"], ["32", "-0.282"], ["36", "-0.322"]], "6": [["6", "1.0"], ["42", "0.403"], ["9", "0.361"], ["49", "0.342"], ["1", "0.338"], ["2", "0.323"], ["41", "0.32"], ["43", "0.314"], ["11", "0.308"], ["7", "0.298"], ["13", "0.274"], ["15", "0.243"], ["5", "0.239"], ["46", "0.237"], ["40", "0.235"], ["48", "0.216"], ["14", "0.208"], ["0", "0.194"], ["31", "0.194"], ["37", "0.191"], ["45", "0.188"], ["28", "0.182"], ["30", "0.174"], ["17", "0.167"], ["34", "0.166"], ["39", "0.155"], ["44", "0.152"], ["20", "0.143"], ["16", "0.134"], ["10", "0.129"], ["33", "0.114"], ["27", "0.109"], ["25", "0.107"], ["18", "0.101"], ["35", "0.094"], ["38", "0.087"], ["24", "0.077"], ["4", "0.067"], ["19", "0.062"], ["3", "0.061"], ["23", "0.053"], ["32", "0.03"], ["22", "0.024"], ["29", "-0.021"], ["26", "-0.034"], ["21", "-0.077"], ["47", "-0.105"], ["36", "-0.129"], ["8", "-0.132"], ["12", "-0.175"]], "7": [["7", "1.0"], ["42", "0.551"], ["9", "0.499"], ["1", "0.491"], ["11", "0.388"], ["49", "0.38"], ["43", "0.38"], ["41", "0.347"], ["15", "0.337"], ["0", "0.336"], ["5", "0.33"], ["46", "0.318"], ["6", "0.298"], ["37", "0.297"], ["13", "0.292"], ["45", "0.292"], ["24", "0.27"], ["31", "0.262"], ["35", "0.209"], ["25", "0.196"], ["2", "0.19"], ["20", "0.189"], ["4", "0.187"], ["3", "0.184"], ["48", "0.172"], ["17", "0.162"], ["18", "0.159"], ["39", "0.155"], ["28", "0.154"], ["30", "0.149"], ["34", "0.149"], ["14", "0.139"], ["29", "0.125"], ["16", "0.123"], ["44", "0.118"], ["32", "0.111"], ["27", "0.098"], ["10", "0.092"], ["23", "0.087"], ["38", "0.083"], ["40", "0.071"], ["26", "0.07"], ["8", "0.058"], ["33", "0.057"], ["19", "0.042"], ["22", "0.042"], ["21", "-0.016"], ["47", "-0.055"], ["12", "-0.063"], ["36", "-0.15"]], "8": [["8", "1.0"], ["26", "0.264"], ["35", "0.261"], ["12", "0.214"], ["3", "0.212"], ["23", "0.21"], ["0", "0.18"], ["31", "0.174"], ["29", "0.168"], ["9", "0.156"], ["24", "0.141"], ["15", "0.132"], ["21", "0.103"], ["10", "0.097"], ["16", "0.081"], ["25", "0.062"], ["7", "0.058"], ["32", "0.049"], ["33", "0.036"], ["41", "0.016"], ["4", "-0.006"], ["17", "-0.015"], ["27", "-0.016"], ["1", "-0.019"], ["42", "-0.023"], ["22", "-0.027"], ["34", "-0.034"], ["14", "-0.037"], ["47", "-0.042"], ["19", "-0.046"], ["5", "-0.048"], ["49", "-0.048"], ["2", "-0.055"], ["18", "-0.066"], ["38", "-0.068"], ["40", "-0.077"], ["36", "-0.084"], ["28", "-0.102"], ["11", "-0.109"], ["13", "-0.11"], ["45", "-0.121"], ["37", "-0.122"], ["39", "-0.125"], ["6", "-0.132"], ["46", "-0.133"], ["30", "-0.152"], ["20", "-0.195"], ["48", "-0.213"], ["43", "-0.284"], ["44", "-0.341"]], "9": [["9", "1.0"], ["0", "0.61"], ["42", "0.523"], ["7", "0.499"], ["15", "0.49"], ["11", "0.435"], ["41", "0.429"], ["10", "0.42"], ["49", "0.412"], ["1", "0.374"], ["6", "0.361"], ["43", "0.328"], ["4", "0.309"], ["3", "0.309"], ["13", "0.296"], ["2", "0.292"], ["31", "0.287"], ["46", "0.284"], ["5", "0.282"], ["24", "0.26"], ["35", "0.217"], ["17", "0.168"], ["8", "0.156"], ["14", "0.152"], ["16", "0.149"], ["39", "0.144"], ["45", "0.14"], ["18", "0.123"], ["37", "0.079"], ["44", "0.074"], ["48", "0.065"], ["34", "0.061"], ["29", "0.06"], ["26", "0.059"], ["25", "0.049"], ["20", "0.042"], ["40", "0.039"], ["12", "-0.039"], ["28", "-0.04"], ["32", "-0.057"], ["27", "-0.057"], ["38", "-0.083"], ["21", "-0.088"], ["23", "-0.098"], ["19", "-0.108"], ["30", "-0.11"], ["47", "-0.115"], ["33", "-0.125"], ["22", "-0.288"], ["36", "-0.323"]], "10": [["10", "1.0"], ["9", "0.42"], ["15", "0.351"], ["0", "0.316"], ["3", "0.261"], ["2", "0.205"], ["4", "0.203"], ["5", "0.174"], ["11", "0.167"], ["42", "0.139"], ["6", "0.129"], ["41", "0.109"], ["14", "0.1"], ["8", "0.097"], ["7", "0.092"], ["13", "0.082"], ["49", "0.08"], ["12", "0.065"], ["1", "0.059"], ["46", "0.058"], ["40", "0.024"], ["48", "0.005"], ["16", "0.003"], ["24", "0.001"], ["31", "-0.005"], ["39", "-0.008"], ["44", "-0.037"], ["17", "-0.038"], ["43", "-0.039"], ["29", "-0.057"], ["35", "-0.067"], ["47", "-0.073"], ["20", "-0.082"], ["45", "-0.093"], ["26", "-0.095"], ["32", "-0.103"], ["38", "-0.113"], ["34", "-0.12"], ["21", "-0.136"], ["25", "-0.142"], ["18", "-0.167"], ["27", "-0.186"], ["28", "-0.202"], ["22", "-0.213"], ["23", "-0.215"], ["19", "-0.217"], ["37", "-0.226"], ["33", "-0.286"], ["30", "-0.295"], ["36", "-0.333"]], "11": [["11", "1.0"], ["42", "0.644"], ["43", "0.608"], ["1", "0.481"], ["5", "0.454"], ["9", "0.435"], ["49", "0.421"], ["46", "0.397"], ["7", "0.388"], ["4", "0.374"], ["48", "0.354"], ["39", "0.326"], ["15", "0.323"], ["44", "0.321"], ["13", "0.317"], ["6", "0.308"], ["41", "0.303"], ["0", "0.266"], ["3", "0.243"], ["14", "0.226"], ["2", "0.179"], ["10", "0.167"], ["45", "0.142"], ["20", "0.132"], ["37", "0.067"], ["40", "0.05"], ["18", "0.048"], ["17", "0.03"], ["16", "-0.004"], ["38", "-0.01"], ["24", "-0.042"], ["19", "-0.073"], ["8", "-0.109"], ["31", "-0.123"], ["47", "-0.147"], ["28", "-0.167"], ["34", "-0.183"], ["25", "-0.184"], ["27", "-0.198"], ["32", "-0.257"], ["30", "-0.259"], ["12", "-0.266"], ["35", "-0.292"], ["22", "-0.294"], ["33", "-0.302"], ["23", "-0.36"], ["36", "-0.374"], ["29", "-0.436"], ["26", "-0.438"], ["21", "-0.457"]], "12": [["12", "1.0"], ["29", "0.348"], ["21", "0.314"], ["26", "0.269"], ["27", "0.245"], ["35", "0.228"], ["34", "0.227"], ["8", "0.214"], ["23", "0.208"], ["16", "0.192"], ["33", "0.177"], ["36", "0.124"], ["19", "0.123"], ["17", "0.107"], ["14", "0.105"], ["30", "0.099"], ["31", "0.095"], ["18", "0.094"], ["10", "0.065"], ["25", "0.062"], ["47", "0.061"], ["0", "0.051"], ["32", "0.046"], ["45", "0.037"], ["24", "0.025"], ["15", "0.022"], ["2", "0.021"], ["28", "0.0"], ["3", "-0.0"], ["5", "-0.002"], ["41", "-0.008"], ["22", "-0.011"], ["38", "-0.022"], ["9", "-0.039"], ["13", "-0.041"], ["4", "-0.045"], ["7", "-0.063"], ["20", "-0.074"], ["40", "-0.104"], ["37", "-0.129"], ["6", "-0.175"], ["48", "-0.181"], ["49", "-0.194"], ["1", "-0.197"], ["42", "-0.2"], ["46", "-0.202"], ["11", "-0.266"], ["39", "-0.273"], ["44", "-0.28"], ["43", "-0.32"]], "13": [["13", "1.0"], ["41", "0.576"], ["17", "0.37"], ["43", "0.366"], ["46", "0.339"], ["14", "0.331"], ["25", "0.33"], ["19", "0.325"], ["11", "0.317"], ["16", "0.316"], ["48", "0.313"], ["27", "0.311"], ["34", "0.296"], ["9", "0.296"], ["7", "0.292"], ["6", "0.274"], ["18", "0.27"], ["2", "0.259"], ["5", "0.247"], ["45", "0.236"], ["20", "0.23"], ["47", "0.224"], ["4", "0.21"], ["30", "0.188"], ["42", "0.188"], ["15", "0.157"], ["1", "0.154"], ["38", "0.149"], ["33", "0.145"], ["28", "0.125"], ["10", "0.082"], ["35", "0.061"], ["0", "0.057"], ["49", "0.035"], ["44", "0.01"], ["31", "-0.001"], ["39", "-0.007"], ["32", "-0.012"], ["40", "-0.014"], ["37", "-0.026"], ["29", "-0.035"], ["12", "-0.041"], ["21", "-0.081"], ["22", "-0.096"], ["8", "-0.11"], ["36", "-0.118"], ["26", "-0.135"], ["23", "-0.14"], ["24", "-0.143"], ["3", "-0.203"]], "14": [["14", "1.0"], ["48", "0.342"], ["41", "0.331"], ["13", "0.331"], ["17", "0.313"], ["20", "0.304"], ["34", "0.241"], ["18", "0.233"], ["11", "0.226"], ["43", "0.217"], ["16", "0.208"], ["6", "0.208"], ["46", "0.195"], ["27", "0.19"], ["4", "0.184"], ["38", "0.178"], ["2", "0.175"], ["45", "0.175"], ["5", "0.173"], ["15", "0.164"], ["19", "0.159"], ["9", "0.152"], ["7", "0.139"], ["30", "0.133"], ["33", "0.131"], ["47", "0.127"], ["1", "0.114"], ["12", "0.105"], ["10", "0.1"], ["40", "0.091"], ["31", "0.071"], ["42", "0.058"], ["25", "0.042"], ["21", "0.037"], ["28", "0.033"], ["0", "0.031"], ["35", "0.025"], ["44", "0.009"], ["3", "0.001"], ["32", "0.0"], ["49", "-0.016"], ["22", "-0.022"], ["36", "-0.025"], ["29", "-0.027"], ["8", "-0.037"], ["39", "-0.039"], ["23", "-0.067"], ["24", "-0.075"], ["26", "-0.087"], ["37", "-0.133"]], "15": [["15", "1.0"], ["9", "0.49"], ["0", "0.424"], ["42", "0.406"], ["3", "0.397"], ["1", "0.356"], ["10", "0.351"], ["7", "0.337"], ["5", "0.324"], ["46", "0.323"], ["11", "0.323"], ["2", "0.291"], ["31", "0.274"], ["49", "0.257"], ["6", "0.243"], ["41", "0.242"], ["24", "0.228"], ["4", "0.212"], ["43", "0.203"], ["14", "0.164"], ["13", "0.157"], ["39", "0.15"], ["44", "0.143"], ["8", "0.132"], ["45", "0.123"], ["40", "0.104"], ["18", "0.094"], ["48", "0.093"], ["35", "0.09"], ["37", "0.061"], ["17", "0.054"], ["34", "0.031"], ["16", "0.028"], ["12", "0.022"], ["20", "0.018"], ["26", "0.005"], ["29", "0.003"], ["32", "-0.035"], ["23", "-0.054"], ["38", "-0.057"], ["28", "-0.078"], ["21", "-0.083"], ["27", "-0.083"], ["25", "-0.084"], ["30", "-0.112"], ["33", "-0.139"], ["19", "-0.14"], ["22", "-0.198"], ["47", "-0.218"], ["36", "-0.26"]], "16": [["16", "1.0"], ["27", "0.437"], ["25", "0.434"], ["19", "0.43"], ["47", "0.343"], ["17", "0.339"], ["33", "0.338"], ["35", "0.321"], ["13", "0.316"], ["34", "0.313"], ["41", "0.289"], ["30", "0.213"], ["14", "0.208"], ["2", "0.198"], ["12", "0.192"], ["29", "0.19"], ["26", "0.183"], ["21", "0.169"], ["23", "0.166"], ["9", "0.149"], ["18", "0.14"], ["45", "0.134"], ["6", "0.134"], ["7", "0.123"], ["28", "0.097"], ["31", "0.087"], ["8", "0.081"], ["4", "0.065"], ["48", "0.041"], ["32", "0.032"], ["15", "0.028"], ["1", "0.025"], ["5", "0.004"], ["10", "0.003"], ["11", "-0.004"], ["46", "-0.008"], ["43", "-0.009"], ["42", "-0.022"], ["36", "-0.023"], ["38", "-0.028"], ["22", "-0.032"], ["40", "-0.034"], ["20", "-0.047"], ["0", "-0.092"], ["24", "-0.118"], ["49", "-0.122"], ["37", "-0.129"], ["44", "-0.227"], ["3", "-0.241"], ["39", "-0.276"]], "17": [["17", "1.0"], ["34", "0.528"], ["27", "0.496"], ["25", "0.464"], ["30", "0.424"], ["41", "0.414"], ["33", "0.377"], ["28", "0.374"], ["35", "0.373"], ["13", "0.37"], ["29", "0.361"], ["19", "0.348"], ["21", "0.346"], ["16", "0.339"], ["14", "0.313"], ["20", "0.28"], ["18", "0.275"], ["47", "0.262"], ["26", "0.247"], ["2", "0.242"], ["48", "0.235"], ["31", "0.232"], ["38", "0.227"], ["45", "0.216"], ["43", "0.18"], ["32", "0.17"], ["9", "0.168"], ["6", "0.167"], ["7", "0.162"], ["40", "0.133"], ["23", "0.113"], ["12", "0.107"], ["24", "0.087"], ["46", "0.082"], ["0", "0.081"], ["37", "0.077"], ["1", "0.07"], ["4", "0.059"], ["15", "0.054"], ["36", "0.037"], ["11", "0.03"], ["22", "0.025"], ["42", "-0.001"], ["8", "-0.015"], ["5", "-0.026"], ["49", "-0.03"], ["10", "-0.038"], ["44", "-0.129"], ["3", "-0.157"], ["39", "-0.241"]], "18": [["18", "1.0"], ["34", "0.39"], ["20", "0.386"], ["41", "0.354"], ["29", "0.328"], ["30", "0.285"], ["21", "0.28"], ["17", "0.275"], ["13", "0.27"], ["43", "0.265"], ["27", "0.263"], ["33", "0.251"], ["45", "0.247"], ["32", "0.243"], ["14", "0.233"], ["35", "0.233"], ["24", "0.231"], ["19", "0.225"], ["25", "0.223"], ["31", "0.216"], ["48", "0.206"], ["46", "0.201"], ["28", "0.197"], ["37", "0.174"], ["38", "0.166"], ["7", "0.159"], ["36", "0.149"], ["16", "0.14"], ["26", "0.136"], ["9", "0.123"], ["1", "0.107"], ["6", "0.101"], ["12", "0.094"], ["15", "0.094"], ["44", "0.079"], ["0", "0.066"], ["39", "0.066"], ["11", "0.048"], ["2", "0.044"], ["4", "0.032"], ["5", "0.025"], ["22", "0.002"], ["23", "-0.01"], ["40", "-0.011"], ["42", "-0.018"], ["47", "-0.038"], ["49", "-0.038"], ["8", "-0.066"], ["3", "-0.09"], ["10", "-0.167"]], "19": [["19", "1.0"], ["25", "0.521"], ["27", "0.489"], ["16", "0.43"], ["33", "0.399"], ["30", "0.373"], ["17", "0.348"], ["13", "0.325"], ["47", "0.318"], ["34", "0.314"], ["28", "0.273"], ["41", "0.227"], ["35", "0.226"], ["18", "0.225"], ["21", "0.222"], ["29", "0.198"], ["23", "0.191"], ["48", "0.176"], ["45", "0.168"], ["14", "0.159"], ["38", "0.156"], ["43", "0.135"], ["12", "0.123"], ["26", "0.117"], ["32", "0.098"], ["46", "0.087"], ["22", "0.067"], ["20", "0.064"], ["6", "0.062"], ["2", "0.054"], ["36", "0.053"], ["7", "0.042"], ["40", "0.023"], ["37", "0.005"], ["4", "0.001"], ["31", "-0.025"], ["1", "-0.036"], ["5", "-0.044"], ["8", "-0.046"], ["11", "-0.073"], ["9", "-0.108"], ["15", "-0.14"], ["24", "-0.142"], ["44", "-0.163"], ["42", "-0.18"], ["10", "-0.217"], ["49", "-0.261"], ["39", "-0.274"], ["0", "-0.321"], ["3", "-0.402"]], "20": [["20", "1.0"], ["38", "0.594"], ["22", "0.46"], ["32", "0.427"], ["48", "0.422"], ["34", "0.4"], ["18", "0.386"], ["43", "0.368"], ["28", "0.334"], ["30", "0.324"], ["14", "0.304"], ["17", "0.28"], ["27", "0.254"], ["13", "0.23"], ["21", "0.223"], ["46", "0.213"], ["2", "0.21"], ["41", "0.203"], ["7", "0.189"], ["24", "0.178"], ["29", "0.173"], ["25", "0.167"], ["36", "0.158"], ["33", "0.152"], ["6", "0.143"], ["11", "0.132"], ["37", "0.12"], ["31", "0.091"], ["39", "0.086"], ["45", "0.085"], ["40", "0.081"], ["0", "0.067"], ["19", "0.064"], ["1", "0.057"], ["9", "0.042"], ["44", "0.037"], ["49", "0.021"], ["15", "0.018"], ["47", "-0.005"], ["5", "-0.021"], ["42", "-0.028"], ["16", "-0.047"], ["35", "-0.049"], ["26", "-0.059"], ["3", "-0.067"], ["12", "-0.074"], ["10", "-0.082"], ["23", "-0.094"], ["4", "-0.142"], ["8", "-0.195"]], "21": [["21", "1.0"], ["29", "0.78"], ["26", "0.654"], ["35", "0.601"], ["30", "0.522"], ["33", "0.505"], ["23", "0.491"], ["34", "0.468"], ["27", "0.447"], ["31", "0.444"], ["25", "0.443"], ["32", "0.421"], ["28", "0.42"], ["24", "0.354"], ["17", "0.346"], ["12", "0.314"], ["22", "0.284"], ["18", "0.28"], ["38", "0.261"], ["36", "0.241"], ["20", "0.223"], ["19", "0.222"], ["40", "0.175"], ["16", "0.169"], ["37", "0.13"], ["45", "0.122"], ["8", "0.103"], ["2", "0.102"], ["47", "0.095"], ["14", "0.037"], ["41", "0.033"], ["0", "0.025"], ["7", "-0.016"], ["48", "-0.057"], ["6", "-0.077"], ["13", "-0.081"], ["15", "-0.083"], ["9", "-0.088"], ["10", "-0.136"], ["1", "-0.145"], ["46", "-0.148"], ["49", "-0.182"], ["3", "-0.187"], ["44", "-0.209"], ["4", "-0.219"], ["43", "-0.241"], ["5", "-0.271"], ["42", "-0.342"], ["39", "-0.36"], ["11", "-0.457"]], "22": [["22", "1.0"], ["32", "0.586"], ["38", "0.49"], ["30", "0.486"], ["20", "0.46"], ["28", "0.45"], ["23", "0.381"], ["33", "0.358"], ["36", "0.326"], ["25", "0.325"], ["27", "0.319"], ["29", "0.289"], ["21", "0.284"], ["34", "0.223"], ["26", "0.218"], ["37", "0.215"], ["24", "0.181"], ["35", "0.135"], ["31", "0.114"], ["40", "0.11"], ["19", "0.067"], ["2", "0.044"], ["7", "0.042"], ["17", "0.025"], ["6", "0.024"], ["48", "0.015"], ["18", "0.002"], ["45", "0.0"], ["47", "-0.007"], ["12", "-0.011"], ["14", "-0.022"], ["8", "-0.027"], ["16", "-0.032"], ["1", "-0.04"], ["39", "-0.066"], ["13", "-0.096"], ["49", "-0.097"], ["46", "-0.103"], ["3", "-0.113"], ["41", "-0.141"], ["43", "-0.155"], ["5", "-0.171"], ["42", "-0.185"], ["0", "-0.191"], ["15", "-0.198"], ["10", "-0.213"], ["44", "-0.214"], ["9", "-0.288"], ["11", "-0.294"], ["4", "-0.461"]], "23": [["23", "1.0"], ["26", "0.736"], ["35", "0.641"], ["31", "0.555"], ["33", "0.545"], ["29", "0.516"], ["21", "0.491"], ["30", "0.49"], ["28", "0.457"], ["25", "0.396"], ["24", "0.385"], ["22", "0.381"], ["27", "0.377"], ["32", "0.349"], ["37", "0.301"], ["34", "0.233"], ["36", "0.214"], ["8", "0.21"], ["12", "0.208"], ["40", "0.203"], ["19", "0.191"], ["16", "0.166"], ["38", "0.141"], ["17", "0.113"], ["2", "0.1"], ["45", "0.098"], ["7", "0.087"], ["6", "0.053"], ["1", "0.036"], ["47", "0.034"], ["49", "0.03"], ["0", "0.019"], ["41", "0.005"], ["18", "-0.01"], ["5", "-0.031"], ["3", "-0.051"], ["15", "-0.054"], ["14", "-0.067"], ["42", "-0.074"], ["20", "-0.094"], ["9", "-0.098"], ["46", "-0.098"], ["48", "-0.126"], ["13", "-0.14"], ["39", "-0.149"], ["44", "-0.178"], ["10", "-0.215"], ["43", "-0.293"], ["4", "-0.31"], ["11", "-0.36"]], "24": [["24", "1.0"], ["31", "0.651"], ["35", "0.525"], ["29", "0.524"], ["26", "0.511"], ["37", "0.483"], ["0", "0.48"], ["32", "0.442"], ["23", "0.385"], ["28", "0.381"], ["21", "0.354"], ["3", "0.344"], ["30", "0.32"], ["49", "0.295"], ["1", "0.279"], ["7", "0.27"], ["39", "0.27"], ["9", "0.26"], ["18", "0.231"], ["15", "0.228"], ["42", "0.197"], ["40", "0.186"], ["22", "0.181"], ["20", "0.178"], ["45", "0.175"], ["2", "0.145"], ["8", "0.141"], ["34", "0.119"], ["33", "0.104"], ["17", "0.087"], ["46", "0.083"], ["6", "0.077"], ["25", "0.077"], ["44", "0.074"], ["41", "0.074"], ["43", "0.063"], ["12", "0.025"], ["36", "0.018"], ["10", "0.001"], ["38", "-0.006"], ["27", "-0.014"], ["48", "-0.042"], ["11", "-0.042"], ["5", "-0.057"], ["14", "-0.075"], ["16", "-0.118"], ["19", "-0.142"], ["13", "-0.143"], ["4", "-0.18"], ["47", "-0.382"]], "25": [["25", "1.0"], ["27", "0.698"], ["30", "0.61"], ["28", "0.587"], ["35", "0.566"], ["29", "0.561"], ["33", "0.542"], ["19", "0.521"], ["26", "0.513"], ["34", "0.509"], ["17", "0.464"], ["21", "0.443"], ["32", "0.443"], ["16", "0.434"], ["23", "0.396"], ["38", "0.379"], ["47", "0.34"], ["13", "0.33"], ["22", "0.325"], ["41", "0.303"], ["45", "0.256"], ["31", "0.226"], ["18", "0.223"], ["7", "0.196"], ["20", "0.167"], ["2", "0.155"], ["37", "0.154"], ["6", "0.107"], ["48", "0.107"], ["40", "0.104"], ["36", "0.09"], ["24", "0.077"], ["8", "0.062"], ["12", "0.062"], ["9", "0.049"], ["14", "0.042"], ["46", "0.027"], ["1", "-0.039"], ["43", "-0.076"], ["15", "-0.084"], ["5", "-0.129"], ["42", "-0.131"], ["10", "-0.142"], ["0", "-0.147"], ["49", "-0.155"], ["4", "-0.16"], ["11", "-0.184"], ["44", "-0.261"], ["3", "-0.361"], ["39", "-0.371"]], "26": [["26", "1.0"], ["35", "0.807"], ["29", "0.795"], ["23", "0.736"], ["21", "0.654"], ["31", "0.63"], ["25", "0.513"], ["24", "0.511"], ["30", "0.498"], ["28", "0.498"], ["33", "0.484"], ["27", "0.41"], ["32", "0.407"], ["34", "0.384"], ["37", "0.276"], ["12", "0.269"], ["8", "0.264"], ["17", "0.247"], ["22", "0.218"], ["0", "0.195"], ["16", "0.183"], ["40", "0.166"], ["36", "0.153"], ["38", "0.145"], ["18", "0.136"], ["45", "0.124"], ["2", "0.123"], ["19", "0.117"], ["7", "0.07"], ["9", "0.059"], ["41", "0.05"], ["47", "0.032"], ["15", "0.005"], ["49", "-0.013"], ["6", "-0.034"], ["3", "-0.039"], ["1", "-0.057"], ["20", "-0.059"], ["14", "-0.087"], ["10", "-0.095"], ["13", "-0.135"], ["48", "-0.147"], ["46", "-0.152"], ["44", "-0.163"], ["42", "-0.163"], ["5", "-0.185"], ["39", "-0.254"], ["4", "-0.277"], ["43", "-0.342"], ["11", "-0.438"]], "27": [["27", "1.0"], ["25", "0.698"], ["30", "0.664"], ["34", "0.643"], ["33", "0.629"], ["28", "0.534"], ["29", "0.504"], ["17", "0.496"], ["19", "0.489"], ["35", "0.488"], ["21", "0.447"], ["32", "0.439"], ["16", "0.437"], ["38", "0.418"], ["26", "0.41"], ["23", "0.377"], ["47", "0.321"], ["22", "0.319"], ["13", "0.311"], ["2", "0.302"], ["41", "0.297"], ["36", "0.289"], ["18", "0.263"], ["20", "0.254"], ["12", "0.245"], ["31", "0.243"], ["45", "0.214"], ["14", "0.19"], ["48", "0.129"], ["40", "0.127"], ["6", "0.109"], ["7", "0.098"], ["37", "0.07"], ["46", "0.065"], ["24", "-0.014"], ["8", "-0.016"], ["43", "-0.052"], ["9", "-0.057"], ["15", "-0.083"], ["5", "-0.091"], ["1", "-0.099"], ["4", "-0.143"], ["0", "-0.151"], ["10", "-0.186"], ["42", "-0.193"], ["11", "-0.198"], ["44", "-0.205"], ["49", "-0.208"], ["39", "-0.31"], ["3", "-0.36"]], "28": [["28", "1.0"], ["30", "0.746"], ["32", "0.617"], ["25", "0.587"], ["29", "0.539"], ["27", "0.534"], ["35", "0.527"], ["26", "0.498"], ["34", "0.483"], ["33", "0.474"], ["23", "0.457"], ["22", "0.45"], ["37", "0.447"], ["31", "0.424"], ["21", "0.42"], ["24", "0.381"], ["38", "0.375"], ["17", "0.374"], ["20", "0.334"], ["19", "0.273"], ["45", "0.266"], ["2", "0.226"], ["48", "0.223"], ["40", "0.201"], ["18", "0.197"], ["36", "0.193"], ["6", "0.182"], ["46", "0.174"], ["41", "0.168"], ["7", "0.154"], ["13", "0.125"], ["16", "0.097"], ["43", "0.051"], ["1", "0.036"], ["14", "0.033"], ["0", "0.032"], ["47", "0.031"], ["49", "0.016"], ["12", "0.0"], ["44", "-0.004"], ["9", "-0.04"], ["42", "-0.061"], ["15", "-0.078"], ["39", "-0.097"], ["8", "-0.102"], ["5", "-0.116"], ["3", "-0.152"], ["11", "-0.167"], ["10", "-0.202"], ["4", "-0.376"]], "29": [["29", "1.0"], ["26", "0.795"], ["21", "0.78"], ["35", "0.775"], ["30", "0.616"], ["31", "0.574"], ["25", "0.561"], ["32", "0.542"], ["28", "0.539"], ["34", "0.531"], ["24", "0.524"], ["23", "0.516"], ["27", "0.504"], ["33", "0.483"], ["17", "0.361"], ["12", "0.348"], ["18", "0.328"], ["22", "0.289"], ["37", "0.287"], ["38", "0.228"], ["45", "0.208"], ["40", "0.2"], ["19", "0.198"], ["36", "0.19"], ["16", "0.19"], ["20", "0.173"], ["0", "0.168"], ["8", "0.168"], ["2", "0.157"], ["7", "0.125"], ["41", "0.114"], ["47", "0.069"], ["9", "0.06"], ["15", "0.003"], ["6", "-0.021"], ["14", "-0.027"], ["13", "-0.035"], ["1", "-0.044"], ["10", "-0.057"], ["49", "-0.084"], ["3", "-0.087"], ["48", "-0.093"], ["46", "-0.123"], ["44", "-0.192"], ["5", "-0.207"], ["42", "-0.221"], ["43", "-0.279"], ["4", "-0.285"], ["39", "-0.33"], ["11", "-0.436"]], "30": [["30", "1.0"], ["28", "0.746"], ["27", "0.664"], ["29", "0.616"], ["25", "0.61"], ["33", "0.602"], ["35", "0.572"], ["34", "0.566"], ["32", "0.549"], ["21", "0.522"], ["26", "0.498"], ["23", "0.49"], ["22", "0.486"], ["31", "0.465"], ["17", "0.424"], ["19", "0.373"], ["37", "0.369"], ["38", "0.357"], ["45", "0.35"], ["36", "0.327"], ["20", "0.324"], ["24", "0.32"], ["18", "0.285"], ["16", "0.213"], ["2", "0.21"], ["41", "0.207"], ["13", "0.188"], ["40", "0.187"], ["48", "0.185"], ["6", "0.174"], ["7", "0.149"], ["47", "0.145"], ["14", "0.133"], ["46", "0.103"], ["12", "0.099"], ["1", "0.032"], ["43", "-0.003"], ["49", "-0.026"], ["44", "-0.058"], ["0", "-0.073"], ["9", "-0.11"], ["5", "-0.111"], ["15", "-0.112"], ["42", "-0.123"], ["8", "-0.152"], ["39", "-0.156"], ["11", "-0.259"], ["3", "-0.287"], ["10", "-0.295"], ["4", "-0.296"]], "31": [["31", "1.0"], ["35", "0.745"], ["24", "0.651"], ["26", "0.63"], ["29", "0.574"], ["23", "0.555"], ["30", "0.465"], ["0", "0.449"], ["21", "0.444"], ["28", "0.424"], ["32", "0.387"], ["33", "0.383"], ["37", "0.329"], ["34", "0.317"], ["2", "0.316"], ["9", "0.287"], ["40", "0.28"], ["15", "0.274"], ["49", "0.273"], ["41", "0.272"], ["7", "0.262"], ["1", "0.256"], ["27", "0.243"], ["17", "0.232"], ["25", "0.226"], ["45", "0.226"], ["18", "0.216"], ["6", "0.194"], ["8", "0.174"], ["3", "0.165"], ["42", "0.155"], ["46", "0.148"], ["22", "0.114"], ["36", "0.101"], ["39", "0.096"], ["12", "0.095"], ["20", "0.091"], ["16", "0.087"], ["14", "0.071"], ["44", "0.053"], ["5", "0.034"], ["13", "-0.001"], ["10", "-0.005"], ["48", "-0.018"], ["19", "-0.025"], ["38", "-0.034"], ["43", "-0.035"], ["11", "-0.123"], ["4", "-0.143"], ["47", "-0.176"]], "32": [["32", "1.0"], ["28", "0.617"], ["22", "0.586"], ["30", "0.549"], ["29", "0.542"], ["35", "0.445"], ["25", "0.443"], ["24", "0.442"], ["27", "0.439"], ["20", "0.427"], ["21", "0.421"], ["26", "0.407"], ["31", "0.387"], ["33", "0.378"], ["34", "0.368"], ["38", "0.366"], ["23", "0.349"], ["36", "0.298"], ["18", "0.243"], ["37", "0.214"], ["17", "0.17"], ["2", "0.142"], ["40", "0.116"], ["7", "0.111"], ["19", "0.098"], ["46", "0.079"], ["45", "0.076"], ["48", "0.061"], ["0", "0.061"], ["8", "0.049"], ["12", "0.046"], ["16", "0.032"], ["41", "0.031"], ["6", "0.03"], ["14", "0.0"], ["13", "-0.012"], ["3", "-0.023"], ["1", "-0.023"], ["39", "-0.033"], ["15", "-0.035"], ["47", "-0.045"], ["9", "-0.057"], ["43", "-0.098"], ["10", "-0.103"], ["49", "-0.161"], ["44", "-0.177"], ["42", "-0.24"], ["11", "-0.257"], ["5", "-0.282"], ["4", "-0.364"]], "33": [["33", "1.0"], ["27", "0.629"], ["30", "0.602"], ["34", "0.556"], ["23", "0.545"], ["35", "0.542"], ["25", "0.542"], ["21", "0.505"], ["26", "0.484"], ["29", "0.483"], ["28", "0.474"], ["19", "0.399"], ["36", "0.392"], ["31", "0.383"], ["32", "0.378"], ["17", "0.377"], ["22", "0.358"], ["16", "0.338"], ["38", "0.294"], ["47", "0.277"], ["18", "0.251"], ["41", "0.244"], ["45", "0.21"], ["12", "0.177"], ["40", "0.162"], ["2", "0.155"], ["20", "0.152"], ["13", "0.145"], ["14", "0.131"], ["6", "0.114"], ["37", "0.114"], ["24", "0.104"], ["7", "0.057"], ["8", "0.036"], ["46", "0.028"], ["48", "0.02"], ["1", "-0.081"], ["43", "-0.114"], ["9", "-0.125"], ["0", "-0.138"], ["15", "-0.139"], ["5", "-0.149"], ["49", "-0.17"], ["39", "-0.185"], ["44", "-0.199"], ["42", "-0.225"], ["4", "-0.225"], ["10", "-0.286"], ["3", "-0.293"], ["11", "-0.302"]], "34": [["34", "1.0"], ["27", "0.643"], ["30", "0.566"], ["33", "0.556"], ["29", "0.531"], ["17", "0.528"], ["25", "0.509"], ["35", "0.49"], ["28", "0.483"], ["21", "0.468"], ["38", "0.41"], ["20", "0.4"], ["18", "0.39"], ["26", "0.384"], ["32", "0.368"], ["41", "0.334"], ["2", "0.32"], ["31", "0.317"], ["19", "0.314"], ["16", "0.313"], ["13", "0.296"], ["36", "0.296"], ["14", "0.241"], ["23", "0.233"], ["37", "0.23"], ["12", "0.227"], ["47", "0.223"], ["22", "0.223"], ["45", "0.21"], ["48", "0.193"], ["6", "0.166"], ["7", "0.149"], ["24", "0.119"], ["40", "0.113"], ["46", "0.072"], ["0", "0.061"], ["9", "0.061"], ["43", "0.053"], ["15", "0.031"], ["1", "-0.004"], ["5", "-0.008"], ["8", "-0.034"], ["49", "-0.08"], ["42", "-0.101"], ["4", "-0.104"], ["10", "-0.12"], ["44", "-0.128"], ["39", "-0.157"], ["11", "-0.183"], ["3", "-0.228"]], "35": [["35", "1.0"], ["26", "0.807"], ["29", "0.775"], ["31", "0.745"], ["23", "0.641"], ["21", "0.601"], ["30", "0.572"], ["25", "0.566"], ["33", "0.542"], ["28", "0.527"], ["24", "0.525"], ["34", "0.49"], ["27", "0.488"], ["32", "0.445"], ["17", "0.373"], ["16", "0.321"], ["0", "0.296"], ["41", "0.293"], ["37", "0.276"], ["8", "0.261"], ["45", "0.255"], ["18", "0.233"], ["12", "0.228"], ["19", "0.226"], ["40", "0.226"], ["2", "0.221"], ["9", "0.217"], ["7", "0.209"], ["36", "0.144"], ["22", "0.135"], ["1", "0.1"], ["6", "0.094"], ["47", "0.091"], ["15", "0.09"], ["49", "0.073"], ["13", "0.061"], ["14", "0.025"], ["38", "-0.009"], ["42", "-0.019"], ["46", "-0.028"], ["20", "-0.049"], ["3", "-0.053"], ["10", "-0.067"], ["5", "-0.101"], ["48", "-0.106"], ["4", "-0.176"], ["44", "-0.186"], ["39", "-0.197"], ["43", "-0.211"], ["11", "-0.292"]], "36": [["36", "1.0"], ["33", "0.392"], ["30", "0.327"], ["22", "0.326"], ["32", "0.298"], ["34", "0.296"], ["27", "0.289"], ["21", "0.241"], ["23", "0.214"], ["38", "0.208"], ["28", "0.193"], ["29", "0.19"], ["20", "0.158"], ["26", "0.153"], ["18", "0.149"], ["35", "0.144"], ["12", "0.124"], ["31", "0.101"], ["25", "0.09"], ["19", "0.053"], ["37", "0.037"], ["17", "0.037"], ["39", "0.021"], ["45", "0.019"], ["24", "0.018"], ["47", "0.005"], ["41", "-0.02"], ["16", "-0.023"], ["14", "-0.025"], ["8", "-0.084"], ["40", "-0.097"], ["13", "-0.118"], ["6", "-0.129"], ["44", "-0.138"], ["48", "-0.139"], ["2", "-0.149"], ["7", "-0.15"], ["46", "-0.163"], ["43", "-0.176"], ["49", "-0.18"], ["0", "-0.191"], ["1", "-0.195"], ["3", "-0.253"], ["15", "-0.26"], ["4", "-0.299"], ["42", "-0.318"], ["5", "-0.322"], ["9", "-0.323"], ["10", "-0.333"], ["11", "-0.374"]], "37": [["37", "1.0"], ["24", "0.483"], ["28", "0.447"], ["49", "0.419"], ["42", "0.387"], ["1", "0.376"], ["30", "0.369"], ["39", "0.334"], ["31", "0.329"], ["44", "0.302"], ["23", "0.301"], ["7", "0.297"], ["45", "0.292"], ["29", "0.287"], ["26", "0.276"], ["35", "0.276"], ["43", "0.257"], ["5", "0.233"], ["34", "0.23"], ["22", "0.215"], ["32", "0.214"], ["0", "0.204"], ["40", "0.202"], ["6", "0.191"], ["18", "0.174"], ["2", "0.174"], ["25", "0.154"], ["38", "0.146"], ["21", "0.13"], ["20", "0.12"], ["33", "0.114"], ["3", "0.11"], ["46", "0.099"], ["9", "0.079"], ["17", "0.077"], ["27", "0.07"], ["11", "0.067"], ["48", "0.063"], ["15", "0.061"], ["36", "0.037"], ["41", "0.011"], ["19", "0.005"], ["13", "-0.026"], ["8", "-0.122"], ["12", "-0.129"], ["16", "-0.129"], ["14", "-0.133"], ["4", "-0.214"], ["10", "-0.226"], ["47", "-0.293"]], "38": [["38", "1.0"], ["20", "0.594"], ["22", "0.49"], ["27", "0.418"], ["34", "0.41"], ["25", "0.379"], ["28", "0.375"], ["32", "0.366"], ["30", "0.357"], ["48", "0.317"], ["33", "0.294"], ["21", "0.261"], ["29", "0.228"], ["17", "0.227"], ["36", "0.208"], ["14", "0.178"], ["18", "0.166"], ["19", "0.156"], ["13", "0.149"], ["37", "0.146"], ["26", "0.145"], ["23", "0.141"], ["43", "0.141"], ["2", "0.133"], ["41", "0.117"], ["46", "0.102"], ["6", "0.087"], ["7", "0.083"], ["45", "0.07"], ["47", "0.045"], ["40", "0.023"], ["24", "-0.006"], ["35", "-0.009"], ["11", "-0.01"], ["44", "-0.022"], ["12", "-0.022"], ["16", "-0.028"], ["31", "-0.034"], ["1", "-0.038"], ["5", "-0.054"], ["15", "-0.057"], ["8", "-0.068"], ["9", "-0.083"], ["39", "-0.097"], ["49", "-0.11"], ["10", "-0.113"], ["42", "-0.114"], ["0", "-0.127"], ["3", "-0.161"], ["4", "-0.226"]], "39": [["39", "1.0"], ["44", "0.447"], ["49", "0.437"], ["42", "0.394"], ["43", "0.389"], ["37", "0.334"], ["11", "0.326"], ["1", "0.289"], ["0", "0.277"], ["24", "0.27"], ["5", "0.26"], ["46", "0.228"], ["3", "0.221"], ["6", "0.155"], ["7", "0.155"], ["15", "0.15"], ["9", "0.144"], ["48", "0.14"], ["31", "0.096"], ["20", "0.086"], ["18", "0.066"], ["4", "0.065"], ["2", "0.036"], ["36", "0.021"], ["45", "0.014"], ["41", "-0.0"], ["40", "-0.003"], ["13", "-0.007"], ["10", "-0.008"], ["32", "-0.033"], ["14", "-0.039"], ["22", "-0.066"], ["28", "-0.097"], ["38", "-0.097"], ["8", "-0.125"], ["23", "-0.149"], ["30", "-0.156"], ["34", "-0.157"], ["33", "-0.185"], ["35", "-0.197"], ["17", "-0.241"], ["26", "-0.254"], ["12", "-0.273"], ["19", "-0.274"], ["16", "-0.276"], ["27", "-0.31"], ["29", "-0.33"], ["21", "-0.36"], ["25", "-0.371"], ["47", "-0.446"]], "40": [["40", "1.0"], ["2", "0.293"], ["31", "0.28"], ["6", "0.235"], ["35", "0.226"], ["1", "0.211"], ["23", "0.203"], ["37", "0.202"], ["28", "0.201"], ["29", "0.2"], ["30", "0.187"], ["24", "0.186"], ["21", "0.175"], ["26", "0.166"], ["33", "0.162"], ["44", "0.157"], ["42", "0.157"], ["17", "0.133"], ["5", "0.127"], ["27", "0.127"], ["49", "0.12"], ["46", "0.117"], ["32", "0.116"], ["34", "0.113"], ["3", "0.113"], ["45", "0.113"], ["22", "0.11"], ["25", "0.104"], ["15", "0.104"], ["14", "0.091"], ["0", "0.09"], ["20", "0.081"], ["48", "0.074"], ["7", "0.071"], ["43", "0.055"], ["11", "0.05"], ["9", "0.039"], ["41", "0.035"], ["10", "0.024"], ["38", "0.023"], ["19", "0.023"], ["47", "0.001"], ["39", "-0.003"], ["18", "-0.011"], ["13", "-0.014"], ["16", "-0.034"], ["4", "-0.076"], ["8", "-0.077"], ["36", "-0.097"], ["12", "-0.104"]], "41": [["41", "1.0"], ["13", "0.576"], ["9", "0.429"], ["17", "0.414"], ["18", "0.354"], ["7", "0.347"], ["43", "0.335"], ["34", "0.334"], ["14", "0.331"], ["6", "0.32"], ["46", "0.312"], ["42", "0.304"], ["25", "0.303"], ["11", "0.303"], ["27", "0.297"], ["35", "0.293"], ["16", "0.289"], ["45", "0.275"], ["31", "0.272"], ["0", "0.263"], ["2", "0.259"], ["1", "0.259"], ["48", "0.246"], ["33", "0.244"], ["15", "0.242"], ["4", "0.228"], ["19", "0.227"], ["5", "0.213"], ["30", "0.207"], ["20", "0.203"], ["49", "0.178"], ["28", "0.168"], ["47", "0.123"], ["38", "0.117"], ["29", "0.114"], ["10", "0.109"], ["24", "0.074"], ["26", "0.05"], ["40", "0.035"], ["21", "0.033"], ["32", "0.031"], ["8", "0.016"], ["37", "0.011"], ["23", "0.005"], ["39", "-0.0"], ["12", "-0.008"], ["44", "-0.016"], ["36", "-0.02"], ["3", "-0.048"], ["22", "-0.141"]], "42": [["42", "1.0"], ["49", "0.719"], ["11", "0.644"], ["1", "0.643"], ["5", "0.577"], ["7", "0.551"], ["9", "0.523"], ["0", "0.477"], ["43", "0.473"], ["15", "0.406"], ["6", "0.403"], ["39", "0.394"], ["3", "0.393"], ["37", "0.387"], ["44", "0.354"], ["41", "0.304"], ["45", "0.281"], ["4", "0.264"], ["2", "0.245"], ["46", "0.235"], ["24", "0.197"], ["13", "0.188"], ["40", "0.157"], ["31", "0.155"], ["10", "0.139"], ["48", "0.132"], ["14", "0.058"], ["17", "-0.001"], ["18", "-0.018"], ["35", "-0.019"], ["16", "-0.022"], ["8", "-0.023"], ["20", "-0.028"], ["28", "-0.061"], ["23", "-0.074"], ["34", "-0.101"], ["38", "-0.114"], ["30", "-0.123"], ["25", "-0.131"], ["26", "-0.163"], ["19", "-0.18"], ["22", "-0.185"], ["27", "-0.193"], ["12", "-0.2"], ["29", "-0.221"], ["33", "-0.225"], ["32", "-0.24"], ["47", "-0.286"], ["36", "-0.318"], ["21", "-0.342"]], "43": [["43", "1.0"], ["11", "0.608"], ["46", "0.482"], ["42", "0.473"], ["48", "0.47"], ["1", "0.425"], ["44", "0.422"], ["39", "0.389"], ["7", "0.38"], ["20", "0.368"], ["13", "0.366"], ["49", "0.337"], ["41", "0.335"], ["9", "0.328"], ["6", "0.314"], ["5", "0.276"], ["18", "0.265"], ["37", "0.257"], ["4", "0.255"], ["14", "0.217"], ["45", "0.205"], ["15", "0.203"], ["0", "0.196"], ["17", "0.18"], ["2", "0.171"], ["38", "0.141"], ["19", "0.135"], ["24", "0.063"], ["40", "0.055"], ["3", "0.055"], ["34", "0.053"], ["28", "0.051"], ["30", "-0.003"], ["16", "-0.009"], ["31", "-0.035"], ["10", "-0.039"], ["27", "-0.052"], ["25", "-0.076"], ["32", "-0.098"], ["47", "-0.105"], ["33", "-0.114"], ["22", "-0.155"], ["36", "-0.176"], ["35", "-0.211"], ["21", "-0.241"], ["29", "-0.279"], ["8", "-0.284"], ["23", "-0.293"], ["12", "-0.32"], ["26", "-0.342"]], "44": [["44", "1.0"], ["39", "0.447"], ["43", "0.422"], ["49", "0.379"], ["42", "0.354"], ["11", "0.321"], ["37", "0.302"], ["46", "0.295"], ["5", "0.289"], ["1", "0.277"], ["48", "0.233"], ["45", "0.168"], ["40", "0.157"], ["6", "0.152"], ["15", "0.143"], ["4", "0.139"], ["0", "0.131"], ["7", "0.118"], ["3", "0.092"], ["18", "0.079"], ["24", "0.074"], ["9", "0.074"], ["2", "0.065"], ["31", "0.053"], ["20", "0.037"], ["13", "0.01"], ["14", "0.009"], ["28", "-0.004"], ["41", "-0.016"], ["38", "-0.022"], ["10", "-0.037"], ["30", "-0.058"], ["34", "-0.128"], ["17", "-0.129"], ["36", "-0.138"], ["26", "-0.163"], ["19", "-0.163"], ["32", "-0.177"], ["23", "-0.178"], ["47", "-0.184"], ["35", "-0.186"], ["29", "-0.192"], ["33", "-0.199"], ["27", "-0.205"], ["21", "-0.209"], ["22", "-0.214"], ["16", "-0.227"], ["25", "-0.261"], ["12", "-0.28"], ["8", "-0.341"]], "45": [["45", "1.0"], ["30", "0.35"], ["37", "0.292"], ["7", "0.292"], ["42", "0.281"], ["41", "0.275"], ["1", "0.269"], ["28", "0.266"], ["25", "0.256"], ["35", "0.255"], ["18", "0.247"], ["13", "0.236"], ["31", "0.226"], ["49", "0.217"], ["17", "0.216"], ["27", "0.214"], ["34", "0.21"], ["33", "0.21"], ["29", "0.208"], ["43", "0.205"], ["6", "0.188"], ["5", "0.18"], ["24", "0.175"], ["14", "0.175"], ["19", "0.168"], ["44", "0.168"], ["48", "0.161"], ["11", "0.142"], ["9", "0.14"], ["16", "0.134"], ["2", "0.127"], ["46", "0.127"], ["26", "0.124"], ["15", "0.123"], ["21", "0.122"], ["40", "0.113"], ["23", "0.098"], ["0", "0.094"], ["20", "0.085"], ["32", "0.076"], ["38", "0.07"], ["4", "0.048"], ["12", "0.037"], ["36", "0.019"], ["39", "0.014"], ["22", "0.0"], ["47", "-0.005"], ["3", "-0.04"], ["10", "-0.093"], ["8", "-0.121"]], "46": [["46", "1.0"], ["43", "0.482"], ["11", "0.397"], ["48", "0.379"], ["13", "0.339"], ["15", "0.323"], ["7", "0.318"], ["41", "0.312"], ["44", "0.295"], ["9", "0.284"], ["1", "0.274"], ["5", "0.267"], ["6", "0.237"], ["42", "0.235"], ["39", "0.228"], ["2", "0.225"], ["20", "0.213"], ["18", "0.201"], ["14", "0.195"], ["4", "0.186"], ["28", "0.174"], ["0", "0.171"], ["31", "0.148"], ["45", "0.127"], ["40", "0.117"], ["30", "0.103"], ["38", "0.102"], ["37", "0.099"], ["19", "0.087"], ["49", "0.085"], ["24", "0.083"], ["17", "0.082"], ["32", "0.079"], ["34", "0.072"], ["27", "0.065"], ["10", "0.058"], ["3", "0.037"], ["33", "0.028"], ["25", "0.027"], ["16", "-0.008"], ["35", "-0.028"], ["47", "-0.034"], ["23", "-0.098"], ["22", "-0.103"], ["29", "-0.123"], ["8", "-0.133"], ["21", "-0.148"], ["26", "-0.152"], ["36", "-0.163"], ["12", "-0.202"]], "47": [["47", "1.0"], ["16", "0.343"], ["25", "0.34"], ["27", "0.321"], ["19", "0.318"], ["33", "0.277"], ["17", "0.262"], ["13", "0.224"], ["34", "0.223"], ["30", "0.145"], ["14", "0.127"], ["41", "0.123"], ["21", "0.095"], ["35", "0.091"], ["29", "0.069"], ["48", "0.067"], ["12", "0.061"], ["4", "0.048"], ["38", "0.045"], ["23", "0.034"], ["2", "0.032"], ["26", "0.032"], ["28", "0.031"], ["36", "0.005"], ["40", "0.001"], ["45", "-0.005"], ["20", "-0.005"], ["22", "-0.007"], ["46", "-0.034"], ["18", "-0.038"], ["8", "-0.042"], ["32", "-0.045"], ["7", "-0.055"], ["10", "-0.073"], ["6", "-0.105"], ["43", "-0.105"], ["9", "-0.115"], ["5", "-0.117"], ["11", "-0.147"], ["31", "-0.176"], ["44", "-0.184"], ["15", "-0.218"], ["1", "-0.231"], ["42", "-0.286"], ["0", "-0.291"], ["37", "-0.293"], ["49", "-0.301"], ["3", "-0.382"], ["24", "-0.382"], ["39", "-0.446"]], "48": [["48", "1.0"], ["43", "0.47"], ["20", "0.422"], ["46", "0.379"], ["11", "0.354"], ["14", "0.342"], ["38", "0.317"], ["13", "0.313"], ["41", "0.246"], ["17", "0.235"], ["44", "0.233"], ["28", "0.223"], ["6", "0.216"], ["5", "0.209"], ["18", "0.206"], ["34", "0.193"], ["30", "0.185"], ["19", "0.176"], ["7", "0.172"], ["45", "0.161"], ["2", "0.16"], ["1", "0.143"], ["39", "0.14"], ["42", "0.132"], ["27", "0.129"], ["4", "0.114"], ["25", "0.107"], ["15", "0.093"], ["49", "0.087"], ["40", "0.074"], ["47", "0.067"], ["9", "0.065"], ["37", "0.063"], ["32", "0.061"], ["16", "0.041"], ["33", "0.02"], ["22", "0.015"], ["10", "0.005"], ["0", "-0.014"], ["31", "-0.018"], ["24", "-0.042"], ["21", "-0.057"], ["29", "-0.093"], ["3", "-0.105"], ["35", "-0.106"], ["23", "-0.126"], ["36", "-0.139"], ["26", "-0.147"], ["12", "-0.181"], ["8", "-0.213"]], "49": [["49", "1.0"], ["42", "0.719"], ["0", "0.489"], ["1", "0.474"], ["39", "0.437"], ["11", "0.421"], ["37", "0.419"], ["9", "0.412"], ["5", "0.396"], ["7", "0.38"], ["44", "0.379"], ["6", "0.342"], ["43", "0.337"], ["3", "0.32"], ["24", "0.295"], ["31", "0.273"], ["15", "0.257"], ["45", "0.217"], ["41", "0.178"], ["2", "0.174"], ["4", "0.126"], ["40", "0.12"], ["48", "0.087"], ["46", "0.085"], ["10", "0.08"], ["35", "0.073"], ["13", "0.035"], ["23", "0.03"], ["20", "0.021"], ["28", "0.016"], ["26", "-0.013"], ["14", "-0.016"], ["30", "-0.026"], ["17", "-0.03"], ["18", "-0.038"], ["8", "-0.048"], ["34", "-0.08"], ["29", "-0.084"], ["22", "-0.097"], ["38", "-0.11"], ["16", "-0.122"], ["25", "-0.155"], ["32", "-0.161"], ["33", "-0.17"], ["36", "-0.18"], ["21", "-0.182"], ["12", "-0.194"], ["27", "-0.208"], ["19", "-0.261"], ["47", "-0.301"]]}